student_portal_crawler/__init__.py
student_portal_crawler/__version__.py
student_portal_crawler/browser.py
student_portal_crawler/error.py
student_portal_crawler/page/__init__.py
student_portal_crawler/page/base.py
student_portal_crawler/parser/__init__.py
student_portal_crawler/parser/base.py
student_portal_crawler/parser/lec_cancel.py
student_portal_crawler/parser/lec_info.py
student_portal_crawler/parser/news.py
student_portal_crawler/parser/static.py
student_portal_crawler/parser/utils.py
student_portal_crawler/shibboleth_login/LICENSE
student_portal_crawler/shibboleth_login/__init__.py
student_portal_crawler/shibboleth_login/login.py
student_portal_crawler/shibboleth_login/test/__init__.py
student_portal_crawler/shibboleth_login/test/test_login.py
student_portal_crawler/test/__init__.py
student_portal_crawler/test/test_base_page.py
student_portal_crawler/test/test_base_parser.py
student_portal_crawler/test/test_browser.py
student_portal_crawler/test/test_lec_cancel_parser.py
student_portal_crawler/test/test_lec_info_parser.py
student_portal_crawler/test/test_news_parser.py
student_portal_crawler/test/test_parser_utils.py
student_portal_crawler-0.1.0a1.dist-info/DESCRIPTION.rst
student_portal_crawler-0.1.0a1.dist-info/METADATA
student_portal_crawler-0.1.0a1.dist-info/RECORD
student_portal_crawler-0.1.0a1.dist-info/WHEEL
student_portal_crawler-0.1.0a1.dist-info/metadata.json
student_portal_crawler-0.1.0a1.dist-info/top_level.txt
