Metadata-Version: 2.0
Name: student-portal-crawler
Version: 0.1.0a1
Summary: Crawler module for KIT Student Portal
Home-page: https://www.aquatan.studio/
Author: Studio Aquatan
Author-email: studioaquatan@mail.poyo.info
License: MIT License
Requires-Dist: beautifulsoup4 (>=4.5.0)
Requires-Dist: lxml (>=4.0.0)
Requires-Dist: requests (>=2.15.0)
